topsis/__init__.py
topsis/topsis.py
Topsis_HarshulDeepSingh_102203259-1.0.0.dist-info/METADATA
Topsis_HarshulDeepSingh_102203259-1.0.0.dist-info/WHEEL
Topsis_HarshulDeepSingh_102203259-1.0.0.dist-info/top_level.txt
Topsis_HarshulDeepSingh_102203259-1.0.0.dist-info/RECORD
