Metadata-Version: 2.1
Name: Topsis-HarshulDeepSingh-102203259
Version: 1.0.0
Summary: A Python package for performing TOPSIS analysis.
Home-page: https://github.com/harshulxo/Topsis-Harshul-102203259
Author: HARSHUL DEEP SINGH
Author-email: singhharshuldeep@gmail.com
Classifier: Programming Language :: Python :: 3
Classifier: License :: OSI Approved :: MIT License
Classifier: Operating System :: OS Independent
Requires-Python: >=3.6
Requires-Dist: numpy
Requires-Dist: pandas
Requires-Dist: openpyxl
